{
    "title": "Biden administration cancels Alaska oil and gas lease sale",
    "id": "STORY_99_DOCUMENT_1",
    "old_id": "6644_0",
    "split": "dev",
    "date": "2022-05-12",
    "topic": "energy",
    "source": "CBS News (Online)",
    "media_ideology": "",
    "relative_ideology": "Right",
    "absolute_ideology": "Lean Right",
    "news": [
        {
            "id": 0,
            "text": "The Biden administration has canceled one of the most high-profile oil and gas lease opportunities pending before the Interior Department."
        },
        {
            "id": 1,
            "text": "The decision, which halts the potential to drill for oil in over 1 million acres in the Cook Inlet in Alaska, comes at a challenging political moment, when gas prices are hitting painful new highs."
        },
        {
            "id": 2,
            "text": "In a statement shared first with CBS News, the Department of the Interior cited a \"lack of industry interest in leasing in the area\" for the decision to \"not move forward\" with the Cook Inlet lease sale."
        },
        {
            "id": 3,
            "text": "The department also halted two leases under consideration for the Gulf of Mexico region because of \"conflicting court rulings that impacted work on these proposed lease sales.\""
        },
        {
            "id": 4,
            "text": "The Interior Department's Bureau of Ocean Energy Management has previously canceled lease sales in Cook Inlet three times \u2014 in 2007, 2008, and 2011 \u2014 also citing \"lack of industry interest\" at the time as the reason for scrapping the sales."
        },
        {
            "id": 5,
            "text": "But Alaska Senator Lisa Murkowski, a Republican, released a statement Friday rejecting the administration's contention that there was not much interest from the industry in the lease sale."
        },
        {
            "id": 6,
            "text": "\"Citing a 'lack of industry interest' is nothing more than fantasy from an administration that shuns U.S. energy production."
        },
        {
            "id": 7,
            "text": "Cook Inlet is the sole source of the natural gas that more than 400,000 people in Southcentral Alaska\u2014and significant military bases that are critical to our national security\u2014depend on,\" Senator Murkowski said."
        },
        {
            "id": 8,
            "text": "\"I can say with full certainty, based on conversations as recently as last night, that Alaska's industry does have interest in lease sales in Cook Inlet."
        },
        {
            "id": 9,
            "text": "To claim otherwise is simply false, not to mention stunningly short-sighted."
        },
        {
            "id": 10,
            "text": "The Biden administration needs to recognize how this decision is going to hurt Alaskans, reverse it immediately, and get the federal oil and gas program back on track now.\""
        },
        {
            "id": 11,
            "text": "Federal law requires the Department of the Interior to stick to a five-year leasing plan for auctioning offshore leases."
        },
        {
            "id": 12,
            "text": "The administration had until the end of the current five-year plan \u2014 set to expire at the end of next month \u2014 to complete these lease sales."
        },
        {
            "id": 13,
            "text": "The sun sets behind an oil drilling rig in Prudhoe Bay, Alaska on March 17, 2011."
        },
        {
            "id": 14,
            "text": "Until now, the White House had remained silent about the massive Alaska lease."
        },
        {
            "id": 15,
            "text": "However, canceling the sale would be in keeping with political promises President Joe Biden made in the name of halting global warming."
        },
        {
            "id": 16,
            "text": "But those promises have become a political challenge in the face of prices at the pump."
        },
        {
            "id": 17,
            "text": "\"They don't want to get hit by the Republicans in light of the high gas prices,\" one environmental advocate told CBS News, speaking on the condition he not be named because of the sensitivity of the topic."
        },
        {
            "id": 18,
            "text": "\"They're getting killed on attacks based on inflation."
        },
        {
            "id": 19,
            "text": "The most visible sign of inflation is high gas prices.\""
        },
        {
            "id": 20,
            "text": "The delicate political situation was evident after a top environmental official showed her hand in an email that copied a CBS News reporter."
        },
        {
            "id": 21,
            "text": "Gina McCarthy, the White House national climate adviser, wrote that \"the Cook inlet sale was canceled."
        },
        {
            "id": 22,
            "text": "It is not proceeding.\""
        },
        {
            "id": 23,
            "text": "Almost immediately, another White House official jumped in to declare that McCarthy got ahead of herself."
        },
        {
            "id": 24,
            "text": "Interior Department officials said a final decision had not been made."
        },
        {
            "id": 25,
            "text": "On Wednesday, though, with time running out, the department made its announcement."
        },
        {
            "id": 26,
            "text": "Frank Macchairola, a top official with the American Petroleum Institute, the country's largest oil and gas trade association, called the cancellation of the Cook Inlet lease \"another example of the administration's lack of commitment to oil and gas development in the US.\""
        },
        {
            "id": 27,
            "text": "\"The President has spoken about the need for additional supplies in the market, but his administration has failed to take action to match that rhetoric,\" Macchairola said, adding that politically it would play \"not well.\""
        },
        {
            "id": 28,
            "text": "\"In the kind of price environment that we're seeing, there are negative consequences to shutting off oil and gas development, both politically and practically,\" he said."
        },
        {
            "id": 29,
            "text": "On Wednesday, the national average price of regular gas hit an all-time high of $4.40, according to AAA."
        },
        {
            "id": 30,
            "text": "For environmental groups, the decision was welcome news."
        },
        {
            "id": 31,
            "text": "The Alaska offshore lease arrangement would have opened drilling opportunities over a span of more than 1 million acres for 40 or more years of production."
        },
        {
            "id": 32,
            "text": "The new activity would have led to new underwater pipelines and platforms in the environmentally-sensitive area."
        },
        {
            "id": 33,
            "text": "Drew Caputo, vice president of litigation for lands, wildlife and oceans for the environmental advocacy group Earthjustice, said more than a decade would pass before those leases could have had an impact on gas prices."
        },
        {
            "id": 34,
            "text": "\"It's good for the climate, which can't handle new oil and gas development,\" Caputo said."
        },
        {
            "id": 35,
            "text": "\"It's good for Cook Inlet because offshore drilling is dangerous and disruptive."
        },
        {
            "id": 36,
            "text": "And it's good for the people of Cook Inlet, including native people, who cherish the inlet in its natural state."
        },
        {
            "id": 37,
            "text": "So it's a really good thing.\""
        },
        {
            "id": 38,
            "text": "Still, any decision that worked against the interests of oil and gas involves political trade-offs."
        },
        {
            "id": 39,
            "text": "According to a recent CBS News poll, Mr. Biden's approval rating is lowest when it comes to the economy and inflation, with 69% of those surveyed disapproving of his handling of inflation."
        },
        {
            "id": 40,
            "text": "Sixty-five percent of respondents said they believed the president \"could do more\" to lower gas prices."
        },
        {
            "id": 41,
            "text": "American Petroleum Institute senior vice president Frank Macchiarola said in a statement, \"Unfortunately, this is becoming a pattern - the administration talks about the need for more supply and acts to restrict it."
        },
        {
            "id": 42,
            "text": "As geopolitical volatility and global energy prices continue to rise, we again urge the administration to end the uncertainty and immediately act on a new five-year program for federal offshore leasing.\""
        },
        {
            "id": 43,
            "text": "But environmentalists argue the climate issue is too important to get caught up in political battles."
        },
        {
            "id": 44,
            "text": "\"The scientists are telling us the time to shift from fossil fuel energy is not years from now,\" Caputo said."
        },
        {
            "id": 45,
            "text": "\"It's today."
        },
        {
            "id": 46,
            "text": "We need to end offshore oil leasing.\""
        }
    ],
    "events": [
        {
            "e_id": 0,
            "token": "canceled",
            "sentence_id": 0,
            "start": 29,
            "end": 37,
            "remove": false,
            "partisanship": "Neutral",
            "ideology": "Neutral",
            "entity": []
        },
        {
            "e_id": 1,
            "token": "pending",
            "sentence_id": 0,
            "start": 99,
            "end": 106,
            "remove": false,
            "partisanship": "Neutral",
            "ideology": "Neutral",
            "entity": []
        },
        {
            "e_id": 2,
            "token": "decision",
            "sentence_id": 1,
            "start": 4,
            "end": 12,
            "remove": false,
            "partisanship": "Neutral",
            "ideology": "Neutral",
            "entity": []
        },
        {
            "e_id": 3,
            "token": "halts",
            "sentence_id": 1,
            "start": 20,
            "end": 25,
            "remove": false,
            "partisanship": "Partisan",
            "ideology": "Right",
            "entity": [
                {
                    "entity_id": 0,
                    "text": "The Biden administration",
                    "ideology": "Left",
                    "sentiment": "Negative",
                    "entityType": "Agent"
                },
                {
                    "entity_id": 1,
                    "text": "Cook Inlet drilling",
                    "ideology": "Right",
                    "sentiment": "Neutral",
                    "entityType": "Patient"
                }
            ],
            "intensity": "Weak"
        },
        {
            "e_id": 4,
            "token": "drill",
            "sentence_id": 1,
            "start": 43,
            "end": 48,
            "remove": false,
            "partisanship": "Neutral",
            "ideology": "Neutral",
            "entity": []
        },
        {
            "e_id": 5,
            "token": "comes",
            "sentence_id": 1,
            "start": 110,
            "end": 115,
            "remove": false,
            "partisanship": "Neutral",
            "ideology": "Neutral",
            "entity": []
        },
        {
            "e_id": 6,
            "token": "hitting",
            "sentence_id": 1,
            "start": 171,
            "end": 178,
            "remove": false,
            "partisanship": "Partisan",
            "ideology": "Right",
            "entity": [
                {
                    "entity_id": 2,
                    "text": "gas prices",
                    "ideology": "Neutral",
                    "sentiment": "Negative",
                    "entityType": "Agent"
                },
                {
                    "entity_id": 0,
                    "text": "The Biden administration",
                    "ideology": "Left",
                    "sentiment": "Negative",
                    "entityType": "Others"
                }
            ],
            "intensity": "Weak"
        },
        {
            "e_id": 7,
            "token": "shared",
            "sentence_id": 2,
            "start": 15,
            "end": 21,
            "remove": false,
            "partisanship": "Neutral",
            "ideology": "Neutral",
            "entity": []
        },
        {
            "e_id": 8,
            "token": "cited",
            "sentence_id": 2,
            "start": 74,
            "end": 79,
            "remove": false,
            "partisanship": "Neutral",
            "ideology": "Neutral",
            "entity": []
        },
        {
            "e_id": 9,
            "token": "decision",
            "sentence_id": 2,
            "start": 141,
            "end": 149,
            "remove": false,
            "partisanship": "Neutral",
            "ideology": "Neutral",
            "entity": []
        },
        {
            "e_id": 10,
            "token": "move",
            "sentence_id": 2,
            "start": 158,
            "end": 162,
            "remove": false,
            "partisanship": "Partisan",
            "ideology": "Right",
            "entity": [
                {
                    "entity_id": 0,
                    "text": "The Biden administration",
                    "ideology": "Left",
                    "sentiment": "Negative",
                    "entityType": "Agent"
                },
                {
                    "entity_id": 1,
                    "text": "Cook Inlet drilling",
                    "ideology": "Right",
                    "sentiment": "Neutral",
                    "entityType": "Patient"
                }
            ],
            "intensity": "Weak"
        },
        {
            "e_id": 11,
            "token": "sale",
            "sentence_id": 2,
            "start": 198,
            "end": 202,
            "remove": false,
            "partisanship": "Neutral",
            "ideology": "Neutral",
            "entity": []
        },
        {
            "e_id": 12,
            "token": "halted",
            "sentence_id": 3,
            "start": 20,
            "end": 26,
            "remove": false,
            "partisanship": "Neutral",
            "ideology": "Neutral",
            "entity": []
        },
        {
            "e_id": 13,
            "token": "rulings",
            "sentence_id": 3,
            "start": 118,
            "end": 125,
            "remove": false,
            "partisanship": "Neutral",
            "ideology": "Neutral",
            "entity": []
        },
        {
            "e_id": 14,
            "token": "impacted",
            "sentence_id": 3,
            "start": 131,
            "end": 139,
            "remove": false,
            "partisanship": "Neutral",
            "ideology": "Neutral",
            "entity": []
        },
        {
            "e_id": 15,
            "token": "work",
            "sentence_id": 3,
            "start": 140,
            "end": 144,
            "remove": false,
            "partisanship": "Neutral",
            "ideology": "Neutral",
            "entity": []
        },
        {
            "e_id": 16,
            "token": "canceled",
            "sentence_id": 4,
            "start": 75,
            "end": 83,
            "remove": false,
            "partisanship": "Neutral",
            "ideology": "Neutral",
            "entity": []
        },
        {
            "e_id": 17,
            "token": "sales",
            "sentence_id": 4,
            "start": 90,
            "end": 95,
            "remove": false,
            "partisanship": "Neutral",
            "ideology": "Neutral",
            "entity": []
        },
        {
            "e_id": 18,
            "token": "citing",
            "sentence_id": 4,
            "start": 155,
            "end": 161,
            "remove": false,
            "partisanship": "Neutral",
            "ideology": "Neutral",
            "entity": []
        },
        {
            "e_id": 19,
            "token": "scrapping",
            "sentence_id": 4,
            "start": 220,
            "end": 229,
            "remove": false,
            "partisanship": "Neutral",
            "ideology": "Neutral",
            "entity": []
        },
        {
            "e_id": 20,
            "token": "sales",
            "sentence_id": 4,
            "start": 234,
            "end": 239,
            "remove": false,
            "partisanship": "Neutral",
            "ideology": "Neutral",
            "entity": []
        },
        {
            "e_id": 21,
            "token": "released",
            "sentence_id": 5,
            "start": 49,
            "end": 57,
            "remove": false,
            "partisanship": "Neutral",
            "ideology": "Neutral",
            "entity": []
        },
        {
            "e_id": 22,
            "token": "rejecting",
            "sentence_id": 5,
            "start": 77,
            "end": 86,
            "remove": false,
            "partisanship": "Neutral",
            "ideology": "Neutral",
            "entity": []
        },
        {
            "e_id": 23,
            "token": "contention",
            "sentence_id": 5,
            "start": 108,
            "end": 118,
            "remove": false,
            "partisanship": "Partisan",
            "ideology": "Right",
            "entity": [
                {
                    "entity_id": 0,
                    "text": "The Biden administration",
                    "ideology": "Left",
                    "sentiment": "Negative",
                    "entityType": "Agent"
                },
                {
                    "entity_id": 1,
                    "text": "Cook Inlet drilling",
                    "ideology": "Right",
                    "sentiment": "Neutral",
                    "entityType": "Patient"
                }
            ],
            "intensity": "Weak"
        },
        {
            "e_id": 24,
            "token": "Citing",
            "sentence_id": 6,
            "start": 1,
            "end": 7,
            "remove": false,
            "partisanship": "Neutral",
            "ideology": "Neutral",
            "entity": []
        },
        {
            "e_id": 25,
            "token": "shuns",
            "sentence_id": 6,
            "start": 95,
            "end": 100,
            "remove": false,
            "partisanship": "Partisan",
            "ideology": "Right",
            "entity": [
                {
                    "entity_id": 0,
                    "text": "The Biden administration",
                    "ideology": "Left",
                    "sentiment": "Negative",
                    "entityType": "Agent"
                },
                {
                    "entity_id": 3,
                    "text": "U.S. energy production",
                    "ideology": "Neutral",
                    "sentiment": "Positive",
                    "entityType": "Patient"
                }
            ],
            "intensity": "Strong"
        },
        {
            "e_id": 26,
            "token": "depend",
            "sentence_id": 7,
            "start": 176,
            "end": 182,
            "remove": false,
            "partisanship": "Partisan",
            "ideology": "Right",
            "entity": [
                {
                    "entity_id": 5,
                    "text": "people in Southcentral Alaska",
                    "ideology": "Neutral",
                    "sentiment": "Neutral",
                    "entityType": "Agent"
                },
                {
                    "entity_id": 0,
                    "text": "The Biden administration",
                    "ideology": "Left",
                    "sentiment": "Negative",
                    "entityType": "Others"
                },
                {
                    "entity_id": 1,
                    "text": "Cook Inlet drilling",
                    "ideology": "Right",
                    "sentiment": "Positive",
                    "entityType": "Patient"
                }
            ],
            "intensity": "Weak"
        },
        {
            "e_id": 27,
            "token": "said",
            "sentence_id": 7,
            "start": 206,
            "end": 210,
            "remove": false,
            "partisanship": "Neutral",
            "ideology": "Neutral",
            "entity": []
        },
        {
            "e_id": 28,
            "token": "say",
            "sentence_id": 8,
            "start": 7,
            "end": 10,
            "remove": false,
            "partisanship": "Neutral",
            "ideology": "Neutral",
            "entity": []
        },
        {
            "e_id": 29,
            "token": "conversations",
            "sentence_id": 8,
            "start": 41,
            "end": 54,
            "remove": false,
            "partisanship": "Neutral",
            "ideology": "Neutral",
            "entity": []
        },
        {
            "e_id": 30,
            "token": "have",
            "sentence_id": 8,
            "start": 110,
            "end": 114,
            "remove": false,
            "partisanship": "Partisan",
            "ideology": "Right",
            "entity": [
                {
                    "entity_id": 5,
                    "text": "people in Southcentral Alaska",
                    "ideology": "Neutral",
                    "sentiment": "Neutral",
                    "entityType": "Agent"
                },
                {
                    "entity_id": 1,
                    "text": "Cook Inlet drilling",
                    "ideology": "Right",
                    "sentiment": "Positive",
                    "entityType": "Patient"
                }
            ],
            "intensity": "Weak"
        },
        {
            "e_id": 31,
            "token": "claim",
            "sentence_id": 9,
            "start": 3,
            "end": 8,
            "remove": false,
            "partisanship": "Neutral",
            "ideology": "Neutral",
            "entity": []
        },
        {
            "e_id": 32,
            "token": "needs",
            "sentence_id": 10,
            "start": 25,
            "end": 30,
            "remove": false,
            "partisanship": "Neutral",
            "ideology": "Neutral",
            "entity": []
        },
        {
            "e_id": 33,
            "token": "recognize",
            "sentence_id": 10,
            "start": 34,
            "end": 43,
            "remove": false,
            "partisanship": "Partisan",
            "ideology": "Right",
            "entity": [
                {
                    "entity_id": 0,
                    "text": "The Biden administration",
                    "ideology": "Left",
                    "sentiment": "Negative",
                    "entityType": "Agent"
                },
                {
                    "entity_id": 5,
                    "text": "people in Southcentral Alaska",
                    "ideology": "Neutral",
                    "sentiment": "Neutral",
                    "entityType": "Patient"
                }
            ],
            "intensity": "Weak"
        },
        {
            "e_id": 34,
            "token": "decision",
            "sentence_id": 10,
            "start": 53,
            "end": 61,
            "remove": false,
            "partisanship": "Neutral",
            "ideology": "Neutral",
            "entity": []
        },
        {
            "e_id": 35,
            "token": "hurt",
            "sentence_id": 10,
            "start": 74,
            "end": 78,
            "remove": false,
            "partisanship": "Partisan",
            "ideology": "Right",
            "entity": [
                {
                    "entity_id": 0,
                    "text": "The Biden administration",
                    "ideology": "Left",
                    "sentiment": "Negative",
                    "entityType": "Agent"
                },
                {
                    "entity_id": 5,
                    "text": "people in Southcentral Alaska",
                    "ideology": "Neutral",
                    "sentiment": "Neutral",
                    "entityType": "Patient"
                }
            ],
            "intensity": "Weak"
        },
        {
            "e_id": 36,
            "token": "reverse",
            "sentence_id": 10,
            "start": 89,
            "end": 96,
            "remove": false,
            "partisanship": "Partisan",
            "ideology": "Right",
            "entity": [
                {
                    "entity_id": 0,
                    "text": "The Biden administration",
                    "ideology": "Left",
                    "sentiment": "Negative",
                    "entityType": "Agent"
                },
                {
                    "entity_id": 1,
                    "text": "Cook Inlet drilling",
                    "ideology": "Right",
                    "sentiment": "Neutral",
                    "entityType": "Patient"
                }
            ],
            "intensity": "Weak"
        },
        {
            "e_id": 37,
            "token": "get",
            "sentence_id": 10,
            "start": 117,
            "end": 120,
            "remove": false,
            "partisanship": "Partisan",
            "ideology": "Right",
            "entity": [
                {
                    "entity_id": 0,
                    "text": "The Biden administration",
                    "ideology": "Left",
                    "sentiment": "Negative",
                    "entityType": "Agent"
                },
                {
                    "entity_id": 1,
                    "text": "Cook Inlet drilling",
                    "ideology": "Right",
                    "sentiment": "Neutral",
                    "entityType": "Patient"
                }
            ],
            "intensity": "Weak"
        },
        {
            "e_id": 38,
            "token": "requires",
            "sentence_id": 11,
            "start": 12,
            "end": 20,
            "remove": false,
            "partisanship": "Neutral",
            "ideology": "Neutral",
            "entity": []
        },
        {
            "e_id": 39,
            "token": "stick",
            "sentence_id": 11,
            "start": 55,
            "end": 60,
            "remove": false,
            "partisanship": "Neutral",
            "ideology": "Neutral",
            "entity": []
        },
        {
            "e_id": 40,
            "token": "auctioning",
            "sentence_id": 11,
            "start": 93,
            "end": 103,
            "remove": false,
            "partisanship": "Neutral",
            "ideology": "Neutral",
            "entity": []
        },
        {
            "e_id": 41,
            "token": "end",
            "sentence_id": 12,
            "start": 33,
            "end": 36,
            "remove": false,
            "partisanship": "Neutral",
            "ideology": "Neutral",
            "entity": []
        },
        {
            "e_id": 42,
            "token": "set",
            "sentence_id": 12,
            "start": 69,
            "end": 72,
            "remove": false,
            "partisanship": "Neutral",
            "ideology": "Neutral",
            "entity": []
        },
        {
            "e_id": 43,
            "token": "expire",
            "sentence_id": 12,
            "start": 76,
            "end": 82,
            "remove": false,
            "partisanship": "Neutral",
            "ideology": "Neutral",
            "entity": []
        },
        {
            "e_id": 44,
            "token": "complete",
            "sentence_id": 12,
            "start": 113,
            "end": 121,
            "remove": false,
            "partisanship": "Partisan",
            "ideology": "Right",
            "entity": [
                {
                    "entity_id": 0,
                    "text": "The Biden administration",
                    "ideology": "Left",
                    "sentiment": "Negative",
                    "entityType": "Agent"
                },
                {
                    "entity_id": 1,
                    "text": "Cook Inlet drilling",
                    "ideology": "Right",
                    "sentiment": "Neutral",
                    "entityType": "Patient"
                }
            ],
            "intensity": "Weak"
        },
        {
            "e_id": 45,
            "token": "sales",
            "sentence_id": 12,
            "start": 134,
            "end": 139,
            "remove": false,
            "partisanship": "Neutral",
            "ideology": "Neutral",
            "entity": []
        },
        {
            "e_id": 46,
            "token": "sets",
            "sentence_id": 13,
            "start": 8,
            "end": 12,
            "remove": false,
            "partisanship": "Neutral",
            "ideology": "Neutral",
            "entity": []
        },
        {
            "e_id": 47,
            "token": "remained",
            "sentence_id": 14,
            "start": 31,
            "end": 39,
            "remove": false,
            "partisanship": "Partisan",
            "ideology": "Right",
            "entity": [
                {
                    "entity_id": 0,
                    "text": "The Biden administration",
                    "ideology": "Left",
                    "sentiment": "Negative",
                    "entityType": "Agent"
                },
                {
                    "entity_id": 1,
                    "text": "Cook Inlet drilling",
                    "ideology": "Right",
                    "sentiment": "Neutral",
                    "entityType": "Patient"
                }
            ],
            "intensity": "Weak"
        },
        {
            "e_id": 48,
            "token": "canceling",
            "sentence_id": 15,
            "start": 9,
            "end": 18,
            "remove": false,
            "partisanship": "Neutral",
            "ideology": "Neutral",
            "entity": []
        },
        {
            "e_id": 49,
            "token": "made",
            "sentence_id": 15,
            "start": 92,
            "end": 96,
            "remove": false,
            "partisanship": "Neutral",
            "ideology": "Neutral",
            "entity": []
        },
        {
            "e_id": 50,
            "token": "halting",
            "sentence_id": 15,
            "start": 112,
            "end": 119,
            "remove": false,
            "partisanship": "Counter-Partisan",
            "ideology": "Left",
            "entity": [
                {
                    "entity_id": 0,
                    "text": "The Biden administration",
                    "ideology": "Left",
                    "sentiment": "Positive",
                    "entityType": "Agent"
                },
                {
                    "entity_id": 6,
                    "text": "global warming",
                    "ideology": "Neutral",
                    "sentiment": "Negative",
                    "entityType": "Patient"
                }
            ]
        },
        {
            "e_id": 51,
            "token": "become",
            "sentence_id": 16,
            "start": 24,
            "end": 30,
            "remove": false,
            "partisanship": "Partisan",
            "ideology": "Right",
            "entity": [
                {
                    "entity_id": 6,
                    "text": "global warming",
                    "ideology": "Neutral",
                    "sentiment": "Neutral",
                    "entityType": "Agent"
                },
                {
                    "entity_id": 2,
                    "text": "gas prices",
                    "ideology": "Neutral",
                    "sentiment": "Negative",
                    "entityType": "Patient"
                },
                {
                    "entity_id": 0,
                    "text": "The Biden administration",
                    "ideology": "Left",
                    "sentiment": "Negative",
                    "entityType": "Others"
                }
            ],
            "intensity": "Weak"
        },
        {
            "e_id": 52,
            "token": "want",
            "sentence_id": 17,
            "start": 12,
            "end": 16,
            "remove": false,
            "partisanship": "Neutral",
            "ideology": "Neutral",
            "entity": []
        },
        {
            "e_id": 53,
            "token": "hit",
            "sentence_id": 17,
            "start": 24,
            "end": 27,
            "remove": false,
            "partisanship": "Partisan",
            "ideology": "Right",
            "entity": [
                {
                    "entity_id": 0,
                    "text": "The Biden administration",
                    "ideology": "Left",
                    "sentiment": "Negative",
                    "entityType": "Agent"
                },
                {
                    "entity_id": 2,
                    "text": "gas prices",
                    "ideology": "Neutral",
                    "sentiment": "Negative",
                    "entityType": "Patient"
                }
            ],
            "intensity": "Weak"
        },
        {
            "e_id": 54,
            "token": "told",
            "sentence_id": 17,
            "start": 108,
            "end": 112,
            "remove": false,
            "partisanship": "Neutral",
            "ideology": "Neutral",
            "entity": []
        },
        {
            "e_id": 55,
            "token": "speaking",
            "sentence_id": 17,
            "start": 123,
            "end": 131,
            "remove": false,
            "partisanship": "Neutral",
            "ideology": "Neutral",
            "entity": []
        },
        {
            "e_id": 56,
            "token": "named",
            "sentence_id": 17,
            "start": 159,
            "end": 164,
            "remove": false,
            "partisanship": "Neutral",
            "ideology": "Neutral",
            "entity": []
        },
        {
            "e_id": 57,
            "token": "killed",
            "sentence_id": 18,
            "start": 17,
            "end": 23,
            "remove": false,
            "partisanship": "Partisan",
            "ideology": "Right",
            "entity": [
                {
                    "entity_id": 0,
                    "text": "The Biden administration",
                    "ideology": "Left",
                    "sentiment": "Negative",
                    "entityType": "Agent"
                },
                {
                    "entity_id": 2,
                    "text": "gas prices",
                    "ideology": "Neutral",
                    "sentiment": "Negative",
                    "entityType": "Patient"
                }
            ],
            "intensity": "Weak"
        },
        {
            "e_id": 58,
            "token": "attacks",
            "sentence_id": 18,
            "start": 27,
            "end": 34,
            "remove": false,
            "partisanship": "Neutral",
            "ideology": "Neutral",
            "entity": []
        },
        {
            "e_id": 59,
            "token": "evident",
            "sentence_id": 20,
            "start": 37,
            "end": 44,
            "remove": false,
            "partisanship": "Neutral",
            "ideology": "Neutral",
            "entity": []
        },
        {
            "e_id": 60,
            "token": "showed",
            "sentence_id": 20,
            "start": 80,
            "end": 86,
            "remove": false,
            "partisanship": "Neutral",
            "ideology": "Neutral",
            "entity": []
        },
        {
            "e_id": 61,
            "token": "copied",
            "sentence_id": 20,
            "start": 113,
            "end": 119,
            "remove": false,
            "partisanship": "Neutral",
            "ideology": "Neutral",
            "entity": []
        },
        {
            "e_id": 62,
            "token": "wrote",
            "sentence_id": 21,
            "start": 57,
            "end": 62,
            "remove": false,
            "partisanship": "Neutral",
            "ideology": "Neutral",
            "entity": []
        },
        {
            "e_id": 63,
            "token": "sale",
            "sentence_id": 21,
            "start": 84,
            "end": 88,
            "remove": false,
            "partisanship": "Neutral",
            "ideology": "Neutral",
            "entity": []
        },
        {
            "e_id": 64,
            "token": "canceled",
            "sentence_id": 21,
            "start": 93,
            "end": 101,
            "remove": false,
            "partisanship": "Neutral",
            "ideology": "Neutral",
            "entity": []
        },
        {
            "e_id": 65,
            "token": "proceeding",
            "sentence_id": 22,
            "start": 10,
            "end": 20,
            "remove": false,
            "partisanship": "Neutral",
            "ideology": "Neutral",
            "entity": []
        },
        {
            "e_id": 66,
            "token": "jumped",
            "sentence_id": 23,
            "start": 49,
            "end": 55,
            "remove": false,
            "partisanship": "Neutral",
            "ideology": "Neutral",
            "entity": []
        },
        {
            "e_id": 67,
            "token": "declare",
            "sentence_id": 23,
            "start": 62,
            "end": 69,
            "remove": false,
            "partisanship": "Neutral",
            "ideology": "Neutral",
            "entity": []
        },
        {
            "e_id": 68,
            "token": "got",
            "sentence_id": 23,
            "start": 84,
            "end": 87,
            "remove": false,
            "partisanship": "Neutral",
            "ideology": "Neutral",
            "entity": []
        },
        {
            "e_id": 69,
            "token": "said",
            "sentence_id": 24,
            "start": 30,
            "end": 34,
            "remove": false,
            "partisanship": "Neutral",
            "ideology": "Neutral",
            "entity": []
        },
        {
            "e_id": 70,
            "token": "decision",
            "sentence_id": 24,
            "start": 43,
            "end": 51,
            "remove": false,
            "partisanship": "Neutral",
            "ideology": "Neutral",
            "entity": []
        },
        {
            "e_id": 71,
            "token": "made",
            "sentence_id": 24,
            "start": 65,
            "end": 69,
            "remove": false,
            "partisanship": "Neutral",
            "ideology": "Neutral",
            "entity": []
        },
        {
            "e_id": 72,
            "token": "running",
            "sentence_id": 25,
            "start": 32,
            "end": 39,
            "remove": false,
            "partisanship": "Partisan",
            "ideology": "Right",
            "entity": [
                {
                    "entity_id": 0,
                    "text": "The Biden administration",
                    "ideology": "Left",
                    "sentiment": "Negative",
                    "entityType": "Agent"
                },
                {
                    "entity_id": 1,
                    "text": "Cook Inlet drilling",
                    "ideology": "Right",
                    "sentiment": "Neutral",
                    "entityType": "Patient"
                }
            ],
            "intensity": "Weak"
        },
        {
            "e_id": 73,
            "token": "made",
            "sentence_id": 25,
            "start": 60,
            "end": 64,
            "remove": false,
            "partisanship": "Neutral",
            "ideology": "Neutral",
            "entity": []
        },
        {
            "e_id": 74,
            "token": "announcement",
            "sentence_id": 25,
            "start": 69,
            "end": 81,
            "remove": false,
            "partisanship": "Neutral",
            "ideology": "Neutral",
            "entity": []
        },
        {
            "e_id": 75,
            "token": "called",
            "sentence_id": 26,
            "start": 126,
            "end": 132,
            "remove": false,
            "partisanship": "Neutral",
            "ideology": "Neutral",
            "entity": []
        },
        {
            "e_id": 76,
            "token": "cancellation",
            "sentence_id": 26,
            "start": 137,
            "end": 149,
            "remove": false,
            "partisanship": "Neutral",
            "ideology": "Neutral",
            "entity": []
        },
        {
            "e_id": 77,
            "token": "spoken",
            "sentence_id": 27,
            "start": 19,
            "end": 25,
            "remove": false,
            "partisanship": "Neutral",
            "ideology": "Neutral",
            "entity": []
        },
        {
            "e_id": 78,
            "token": "failed",
            "sentence_id": 27,
            "start": 107,
            "end": 113,
            "remove": false,
            "partisanship": "Partisan",
            "ideology": "Right",
            "entity": [
                {
                    "entity_id": 0,
                    "text": "The Biden administration",
                    "ideology": "Left",
                    "sentiment": "Negative",
                    "entityType": "Agent"
                },
                {
                    "entity_id": 1,
                    "text": "Cook Inlet drilling",
                    "ideology": "Right",
                    "sentiment": "Neutral",
                    "entityType": "Patient"
                }
            ],
            "intensity": "Weak"
        },
        {
            "e_id": 79,
            "token": "take",
            "sentence_id": 27,
            "start": 117,
            "end": 121,
            "remove": false,
            "partisanship": "Neutral",
            "ideology": "Neutral",
            "entity": []
        },
        {
            "e_id": 80,
            "token": "match",
            "sentence_id": 27,
            "start": 132,
            "end": 137,
            "remove": false,
            "partisanship": "Neutral",
            "ideology": "Neutral",
            "entity": []
        },
        {
            "e_id": 81,
            "token": "said",
            "sentence_id": 27,
            "start": 166,
            "end": 170,
            "remove": false,
            "partisanship": "Neutral",
            "ideology": "Neutral",
            "entity": []
        },
        {
            "e_id": 82,
            "token": "adding",
            "sentence_id": 27,
            "start": 172,
            "end": 178,
            "remove": false,
            "partisanship": "Neutral",
            "ideology": "Neutral",
            "entity": []
        },
        {
            "e_id": 83,
            "token": "play",
            "sentence_id": 27,
            "start": 205,
            "end": 209,
            "remove": false,
            "partisanship": "Partisan",
            "ideology": "Right",
            "entity": [
                {
                    "entity_id": 0,
                    "text": "The Biden administration",
                    "ideology": "Left",
                    "sentiment": "Negative",
                    "entityType": "Agent"
                },
                {
                    "entity_id": 1,
                    "text": "Cook Inlet drilling",
                    "ideology": "Right",
                    "sentiment": "Neutral",
                    "entityType": "Patient"
                }
            ],
            "intensity": "Weak"
        },
        {
            "e_id": 84,
            "token": "seeing",
            "sentence_id": 28,
            "start": 45,
            "end": 51,
            "remove": false,
            "partisanship": "Neutral",
            "ideology": "Neutral",
            "entity": []
        },
        {
            "e_id": 85,
            "token": "shutting",
            "sentence_id": 28,
            "start": 88,
            "end": 96,
            "remove": false,
            "partisanship": "Partisan",
            "ideology": "Right",
            "entity": [
                {
                    "entity_id": 0,
                    "text": "The Biden administration",
                    "ideology": "Left",
                    "sentiment": "Negative",
                    "entityType": "Agent"
                },
                {
                    "entity_id": 1,
                    "text": "Cook Inlet drilling",
                    "ideology": "Right",
                    "sentiment": "Neutral",
                    "entityType": "Patient"
                }
            ],
            "intensity": "Weak"
        },
        {
            "e_id": 86,
            "token": "said",
            "sentence_id": 28,
            "start": 164,
            "end": 168,
            "remove": false,
            "partisanship": "Neutral",
            "ideology": "Neutral",
            "entity": []
        },
        {
            "e_id": 87,
            "token": "hit",
            "sentence_id": 29,
            "start": 56,
            "end": 59,
            "remove": false,
            "partisanship": "Partisan",
            "ideology": "Right",
            "entity": [
                {
                    "entity_id": 2,
                    "text": "gas prices",
                    "ideology": "Neutral",
                    "sentiment": "Negative",
                    "entityType": "Agent"
                },
                {
                    "entity_id": 0,
                    "text": "The Biden administration",
                    "ideology": "Left",
                    "sentiment": "Negative",
                    "entityType": "Patient"
                }
            ],
            "intensity": "Weak"
        },
        {
            "e_id": 88,
            "token": "according",
            "sentence_id": 29,
            "start": 87,
            "end": 96,
            "remove": false,
            "partisanship": "Neutral",
            "ideology": "Neutral",
            "entity": []
        },
        {
            "e_id": 89,
            "token": "decision",
            "sentence_id": 30,
            "start": 30,
            "end": 38,
            "remove": false,
            "partisanship": "Counter-Partisan",
            "ideology": "Left",
            "entity": [
                {
                    "entity_id": 0,
                    "text": "The Biden administration",
                    "ideology": "Left",
                    "sentiment": "Positive",
                    "entityType": "Agent"
                },
                {
                    "entity_id": 6,
                    "text": "global warming",
                    "ideology": "Neutral",
                    "sentiment": "Neutral",
                    "entityType": "Patient"
                }
            ]
        },
        {
            "e_id": 90,
            "token": "opened",
            "sentence_id": 31,
            "start": 49,
            "end": 55,
            "remove": false,
            "partisanship": "Partisan",
            "ideology": "Right",
            "entity": [
                {
                    "entity_id": 1,
                    "text": "Cook Inlet drilling",
                    "ideology": "Right",
                    "sentiment": "Positive",
                    "entityType": "Agent"
                },
                {
                    "entity_id": 3,
                    "text": "U.S. energy production",
                    "ideology": "Neutral",
                    "sentiment": "Positive",
                    "entityType": "Patient"
                }
            ],
            "intensity": "Weak"
        },
        {
            "e_id": 91,
            "token": "led",
            "sentence_id": 32,
            "start": 28,
            "end": 31,
            "remove": false,
            "partisanship": "Partisan",
            "ideology": "Right",
            "entity": [
                {
                    "entity_id": 1,
                    "text": "Cook Inlet drilling",
                    "ideology": "Right",
                    "sentiment": "Positive",
                    "entityType": "Agent"
                },
                {
                    "entity_id": 3,
                    "text": "U.S. energy production",
                    "ideology": "Neutral",
                    "sentiment": "Positive",
                    "entityType": "Patient"
                }
            ],
            "intensity": "Weak"
        },
        {
            "e_id": 92,
            "token": "said",
            "sentence_id": 33,
            "start": 124,
            "end": 128,
            "remove": false,
            "partisanship": "Neutral",
            "ideology": "Neutral",
            "entity": []
        },
        {
            "e_id": 93,
            "token": "pass",
            "sentence_id": 33,
            "start": 154,
            "end": 158,
            "remove": false,
            "partisanship": "Neutral",
            "ideology": "Neutral",
            "entity": []
        },
        {
            "e_id": 94,
            "token": "had",
            "sentence_id": 33,
            "start": 190,
            "end": 193,
            "remove": false,
            "partisanship": "Counter-Partisan",
            "ideology": "Left",
            "entity": [
                {
                    "entity_id": 1,
                    "text": "Cook Inlet drilling",
                    "ideology": "Right",
                    "sentiment": "Negative",
                    "entityType": "Agent"
                },
                {
                    "entity_id": 2,
                    "text": "gas prices",
                    "ideology": "Neutral",
                    "sentiment": "Neutral",
                    "entityType": "Patient"
                }
            ]
        },
        {
            "e_id": 95,
            "token": "impact",
            "sentence_id": 33,
            "start": 197,
            "end": 203,
            "remove": false,
            "partisanship": "Neutral",
            "ideology": "Neutral",
            "entity": []
        },
        {
            "e_id": 96,
            "token": "said",
            "sentence_id": 34,
            "start": 84,
            "end": 88,
            "remove": false,
            "partisanship": "Neutral",
            "ideology": "Neutral",
            "entity": []
        },
        {
            "e_id": 97,
            "token": "cherish",
            "sentence_id": 36,
            "start": 73,
            "end": 80,
            "remove": false,
            "partisanship": "Counter-Partisan",
            "ideology": "Left",
            "entity": [
                {
                    "entity_id": 5,
                    "text": "people in Southcentral Alaska",
                    "ideology": "Neutral",
                    "sentiment": "Neutral",
                    "entityType": "Agent"
                },
                {
                    "entity_id": 1,
                    "text": "Cook Inlet drilling",
                    "ideology": "Right",
                    "sentiment": "Negative",
                    "entityType": "Patient"
                }
            ]
        },
        {
            "e_id": 98,
            "token": "decision",
            "sentence_id": 38,
            "start": 11,
            "end": 19,
            "remove": false,
            "partisanship": "Neutral",
            "ideology": "Neutral",
            "entity": []
        },
        {
            "e_id": 99,
            "token": "worked",
            "sentence_id": 38,
            "start": 25,
            "end": 31,
            "remove": false,
            "partisanship": "Neutral",
            "ideology": "Neutral",
            "entity": []
        },
        {
            "e_id": 100,
            "token": "involves",
            "sentence_id": 38,
            "start": 69,
            "end": 77,
            "remove": false,
            "partisanship": "Neutral",
            "ideology": "Neutral",
            "entity": []
        },
        {
            "e_id": 101,
            "token": "surveyed",
            "sentence_id": 39,
            "start": 137,
            "end": 145,
            "remove": false,
            "partisanship": "Neutral",
            "ideology": "Neutral",
            "entity": []
        },
        {
            "e_id": 102,
            "token": "disapproving",
            "sentence_id": 39,
            "start": 146,
            "end": 158,
            "remove": false,
            "partisanship": "Neutral",
            "ideology": "Neutral",
            "entity": []
        },
        {
            "e_id": 103,
            "token": "handling",
            "sentence_id": 39,
            "start": 166,
            "end": 174,
            "remove": false,
            "partisanship": "Partisan",
            "ideology": "Right",
            "entity": [
                {
                    "entity_id": 0,
                    "text": "The Biden administration",
                    "ideology": "Left",
                    "sentiment": "Negative",
                    "entityType": "Agent"
                },
                {
                    "entity_id": 7,
                    "text": "inflation",
                    "ideology": "Neutral",
                    "sentiment": "Negative",
                    "entityType": "Patient"
                }
            ],
            "intensity": "Weak"
        },
        {
            "e_id": 104,
            "token": "said",
            "sentence_id": 40,
            "start": 34,
            "end": 38,
            "remove": false,
            "partisanship": "Neutral",
            "ideology": "Neutral",
            "entity": []
        },
        {
            "e_id": 105,
            "token": "believed",
            "sentence_id": 40,
            "start": 44,
            "end": 52,
            "remove": false,
            "partisanship": "Neutral",
            "ideology": "Neutral",
            "entity": []
        },
        {
            "e_id": 106,
            "token": "do",
            "sentence_id": 40,
            "start": 74,
            "end": 76,
            "remove": false,
            "partisanship": "Partisan",
            "ideology": "Right",
            "entity": [
                {
                    "entity_id": 0,
                    "text": "The Biden administration",
                    "ideology": "Left",
                    "sentiment": "Negative",
                    "entityType": "Agent"
                },
                {
                    "entity_id": 2,
                    "text": "gas prices",
                    "ideology": "Neutral",
                    "sentiment": "Negative",
                    "entityType": "Patient"
                }
            ],
            "intensity": "Weak"
        },
        {
            "e_id": 107,
            "token": "lower",
            "sentence_id": 40,
            "start": 86,
            "end": 91,
            "remove": false,
            "partisanship": "Partisan",
            "ideology": "Right",
            "entity": [
                {
                    "entity_id": 0,
                    "text": "The Biden administration",
                    "ideology": "Left",
                    "sentiment": "Negative",
                    "entityType": "Agent"
                },
                {
                    "entity_id": 2,
                    "text": "gas prices",
                    "ideology": "Neutral",
                    "sentiment": "Negative",
                    "entityType": "Patient"
                }
            ],
            "intensity": "Weak"
        },
        {
            "e_id": 108,
            "token": "said",
            "sentence_id": 41,
            "start": 69,
            "end": 73,
            "remove": false,
            "partisanship": "Neutral",
            "ideology": "Neutral",
            "entity": []
        },
        {
            "e_id": 109,
            "token": "becoming",
            "sentence_id": 41,
            "start": 114,
            "end": 122,
            "remove": false,
            "partisanship": "Neutral",
            "ideology": "Neutral",
            "entity": []
        },
        {
            "e_id": 110,
            "token": "talks",
            "sentence_id": 41,
            "start": 154,
            "end": 159,
            "remove": false,
            "partisanship": "Neutral",
            "ideology": "Neutral",
            "entity": []
        },
        {
            "e_id": 111,
            "token": "acts",
            "sentence_id": 41,
            "start": 195,
            "end": 199,
            "remove": false,
            "partisanship": "Neutral",
            "ideology": "Neutral",
            "entity": []
        },
        {
            "e_id": 112,
            "token": "restrict",
            "sentence_id": 41,
            "start": 203,
            "end": 211,
            "remove": false,
            "partisanship": "Partisan",
            "ideology": "Right",
            "entity": [
                {
                    "entity_id": 0,
                    "text": "The Biden administration",
                    "ideology": "Left",
                    "sentiment": "Negative",
                    "entityType": "Agent"
                },
                {
                    "entity_id": 3,
                    "text": "U.S. energy production",
                    "ideology": "Neutral",
                    "sentiment": "Neutral",
                    "entityType": "Patient"
                }
            ],
            "intensity": "Weak"
        },
        {
            "e_id": 113,
            "token": "continue",
            "sentence_id": 42,
            "start": 52,
            "end": 60,
            "remove": false,
            "partisanship": "Neutral",
            "ideology": "Neutral",
            "entity": []
        },
        {
            "e_id": 114,
            "token": "rise",
            "sentence_id": 42,
            "start": 64,
            "end": 68,
            "remove": false,
            "partisanship": "Neutral",
            "ideology": "Neutral",
            "entity": []
        },
        {
            "e_id": 115,
            "token": "urge",
            "sentence_id": 42,
            "start": 79,
            "end": 83,
            "remove": false,
            "partisanship": "Neutral",
            "ideology": "Neutral",
            "entity": []
        },
        {
            "e_id": 116,
            "token": "end",
            "sentence_id": 42,
            "start": 106,
            "end": 109,
            "remove": false,
            "partisanship": "Partisan",
            "ideology": "Right",
            "entity": [
                {
                    "entity_id": 0,
                    "text": "The Biden administration",
                    "ideology": "Left",
                    "sentiment": "Negative",
                    "entityType": "Agent"
                },
                {
                    "entity_id": 1,
                    "text": "Cook Inlet drilling",
                    "ideology": "Right",
                    "sentiment": "Neutral",
                    "entityType": "Patient"
                }
            ],
            "intensity": "Weak"
        },
        {
            "e_id": 117,
            "token": "act",
            "sentence_id": 42,
            "start": 142,
            "end": 145,
            "remove": false,
            "partisanship": "Neutral",
            "ideology": "Neutral",
            "entity": []
        },
        {
            "e_id": 118,
            "token": "argue",
            "sentence_id": 43,
            "start": 22,
            "end": 27,
            "remove": false,
            "partisanship": "Neutral",
            "ideology": "Neutral",
            "entity": []
        },
        {
            "e_id": 119,
            "token": "get",
            "sentence_id": 43,
            "start": 66,
            "end": 69,
            "remove": false,
            "partisanship": "Neutral",
            "ideology": "Neutral",
            "entity": []
        },
        {
            "e_id": 120,
            "token": "caught",
            "sentence_id": 43,
            "start": 70,
            "end": 76,
            "remove": false,
            "partisanship": "Neutral",
            "ideology": "Neutral",
            "entity": []
        },
        {
            "e_id": 121,
            "token": "battles",
            "sentence_id": 43,
            "start": 93,
            "end": 100,
            "remove": false,
            "partisanship": "Neutral",
            "ideology": "Neutral",
            "entity": []
        },
        {
            "e_id": 122,
            "token": "telling",
            "sentence_id": 44,
            "start": 20,
            "end": 27,
            "remove": false,
            "partisanship": "Neutral",
            "ideology": "Neutral",
            "entity": []
        },
        {
            "e_id": 123,
            "token": "shift",
            "sentence_id": 44,
            "start": 43,
            "end": 48,
            "remove": false,
            "partisanship": "Neutral",
            "ideology": "Neutral",
            "entity": []
        },
        {
            "e_id": 124,
            "token": "said",
            "sentence_id": 44,
            "start": 104,
            "end": 108,
            "remove": false,
            "partisanship": "Neutral",
            "ideology": "Neutral",
            "entity": []
        },
        {
            "e_id": 125,
            "token": "need",
            "sentence_id": 46,
            "start": 3,
            "end": 7,
            "remove": false,
            "partisanship": "Neutral",
            "ideology": "Neutral",
            "entity": []
        },
        {
            "e_id": 126,
            "token": "end",
            "sentence_id": 46,
            "start": 11,
            "end": 14,
            "remove": false,
            "partisanship": "Counter-Partisan",
            "ideology": "Left",
            "entity": [
                {
                    "entity_id": 1,
                    "text": "Cook Inlet drilling",
                    "ideology": "Right",
                    "sentiment": "Negative",
                    "entityType": "Agent"
                },
                {
                    "entity_id": 6,
                    "text": "global warming",
                    "ideology": "Neutral",
                    "sentiment": "Negative",
                    "entityType": "Patient"
                }
            ]
        }
    ],
    "entity_list": [
        {
            "text": "The Biden administration",
            "ideology": "Left",
            "id": 0,
            "events": [
                3,
                6,
                25,
                26,
                10,
                23,
                33,
                35,
                36,
                37,
                44,
                47,
                50,
                51,
                53,
                57,
                72,
                78,
                83,
                85,
                87,
                89,
                103,
                106,
                107,
                112,
                116
            ]
        },
        {
            "text": "Cook Inlet drilling",
            "ideology": "Right",
            "id": 1,
            "events": [
                3,
                10,
                23,
                26,
                30,
                36,
                37,
                44,
                47,
                72,
                78,
                83,
                85,
                90,
                91,
                94,
                97,
                116,
                126
            ]
        },
        {
            "text": "gas prices",
            "ideology": "Neutral",
            "id": 2,
            "events": [
                6,
                51,
                53,
                57,
                87,
                94,
                106,
                107
            ]
        },
        {
            "text": "U.S. energy production",
            "ideology": "Neutral",
            "id": 3,
            "events": [
                25,
                90,
                91,
                112
            ]
        },
        {
            "text": "people in Southcentral Alaska",
            "ideology": "Neutral",
            "id": 5,
            "events": [
                26,
                30,
                33,
                35,
                97
            ]
        },
        {
            "text": "global warming",
            "ideology": "Neutral",
            "id": 6,
            "events": [
                50,
                51,
                89,
                126
            ]
        },
        {
            "text": "inflation",
            "ideology": "Neutral",
            "id": 7,
            "events": [
                103
            ]
        }
    ]
}